MANIFEST.in
README.md
setup.py
simMachines/Authenticate.py
simMachines/GridSearch.py
simMachines/__init__.py
simMachines/simClassify.py
simMachines/simClassifyPlus.py
simMachines/simRecommend.py
simMachines/simSearch.py
simMachines.egg-info/PKG-INFO
simMachines.egg-info/SOURCES.txt
simMachines.egg-info/dependency_links.txt
simMachines.egg-info/requires.txt
simMachines.egg-info/top_level.txt