Metadata-Version: 1.2
Name: simMachines
Version: 1.2.7
Summary: A library to use simMachines, Inc. API
Home-page: UNKNOWN
Author: Rick Palmer
Author-email: rickpalmer@simmachines.com
License: UNKNOWN
Platform: UNKNOWN
Requires-Python: >=3
